README.md
setup.py
tests/__init__.py
tests/test_core.py
tests/test_wallets.py
uledger.egg-info/PKG-INFO
uledger.egg-info/SOURCES.txt
uledger.egg-info/dependency_links.txt
uledger.egg-info/requires.txt
uledger.egg-info/top_level.txt
uledgersdk/__init__.py
uledgersdk/core.py
uledgersdk/exceptions.py