Metadata-Version: 2.1
Name: uledger
Version: 0.1.5
Summary: ULedger's Python SDK
Author: Carlomagno Amaya
Author-email: carlomagno@uledger.io
License: MIT
Project-URL: Documentation, https://docs.uledger.io/python
Keywords: uledger sdk api
Classifier: Development Status :: 3 - Alpha
Classifier: Intended Audience :: Developers
Classifier: Programming Language :: Python :: 3
Classifier: Programming Language :: Python :: 3.7
Classifier: Programming Language :: Python :: 3.8
Classifier: Programming Language :: Python :: 3.9
Requires-Dist: requests
Requires-Dist: ecdsa
Requires-Dist: datetime
Requires-Dist: urllib3
Requires-Dist: cryptography
